Alt/Common/__init__.py
Alt/Common/ensureXTablesServer.py
Alt/Common/files.py
Alt/Common/network.py
Alt/Common/timeFmt.py
Alt/Constants/AgentConstants.py
Alt/Constants/Field.py
Alt/Constants/Teams.py
Alt/Constants/__init__.py
Alt/Core/Neo.py
Alt/Core/__init__.py
Alt/Core/Agents/Agent.py
Alt/Core/Agents/AgentExample.py
Alt/Core/Agents/__init__.py
Alt/Core/Operators/AgentOperator.py
Alt/Core/Operators/ConfigOperator.py
Alt/Core/Operators/FlaskOperator.py
Alt/Core/Operators/LogOperator.py
Alt/Core/Operators/LogStreamOperator.py
Alt/Core/Operators/OrderOperator.py
Alt/Core/Operators/PropertyOperator.py
Alt/Core/Operators/ShareOperator.py
Alt/Core/Operators/StreamOperator.py
Alt/Core/Operators/TimeOperator.py
Alt/Core/Operators/UpdateOperator.py
Alt/Core/Operators/__init__.py
Alt/Core/Orders/Order.py
Alt/Core/Orders/OrderExample.py
Alt/Core/Orders/__init__.py
Alt/Units/Conversions.py
Alt/Units/Measurements.py
Alt/Units/Types.py
Alt/Units/__init__.py
matrix_alt_core-0.0.1.dist-info/licenses/LICENSE.txt
matrix_alt_core-0.0.1.dist-info/METADATA
matrix_alt_core-0.0.1.dist-info/WHEEL
matrix_alt_core-0.0.1.dist-info/top_level.txt
matrix_alt_core-0.0.1.dist-info/RECORD
