Metadata-Version: 2.4
Name: Matrix-Alt-Core
Version: 0.0.1
Summary: Matrix-Alt-Core is a Matrix-themed Python framework that simplifies defining and running Agents. Agents are tasks that you can easily customize by overriding methods, with built-in support for parallel execution, logging, dynamic properties, and more.
Home-page: https://github.com/Team488/Alt
Author: The Matrix 488
Author-email: 488matrix@gmail.com
Project-URL: Bug Tracker, https://github.com/Team488/Alt/issues
Project-URL: repository, https://github.com/Team488/Alt
Classifier: Programming Language :: Python :: 3
Classifier: License :: OSI Approved :: MIT License
Classifier: Operating System :: OS Independent
Requires-Python: >=3.9
License-File: LICENSE.txt
Requires-Dist: Flask==3.1.0
Requires-Dist: XTablesClient==5.7.9
Requires-Dist: numpy==2.0.2
Requires-Dist: opencv-python==4.11.0.86
Dynamic: license-file
